gemini_research_mcp/__init__.py
gemini_research_mcp/citations.py
gemini_research_mcp/clarifier.py
gemini_research_mcp/config.py
gemini_research_mcp/deep.py
gemini_research_mcp/export.py
gemini_research_mcp/py.typed
gemini_research_mcp/quick.py
gemini_research_mcp/server.py
gemini_research_mcp/storage.py
gemini_research_mcp/types.py
gemini_research_mcp-0.6.5.dist-info/METADATA
gemini_research_mcp-0.6.5.dist-info/WHEEL
gemini_research_mcp-0.6.5.dist-info/entry_points.txt
gemini_research_mcp-0.6.5.dist-info/licenses/LICENSE
gemini_research_mcp-0.6.5.dist-info/RECORD
