Metadata-Version: 2.4
Name: gemini-research-mcp
Version: 0.6.5
Summary: MCP server for AI-powered research using Gemini: quick grounded search + Deep Research Agent
Project-URL: Homepage, https://github.com/machinemates-ai/gemini-research-mcp
Project-URL: Documentation, https://github.com/machinemates-ai/gemini-research-mcp#readme
Project-URL: Repository, https://github.com/machinemates-ai/gemini-research-mcp
Project-URL: Issues, https://github.com/machinemates-ai/gemini-research-mcp/issues
Author-email: Guillaume Fortaine <guillaume.fortaine+github@machinemates.ai>
License-Expression: MIT
License-File: LICENSE
Keywords: ai,deep-research,gemini,google-search,grounding,mcp,model-context-protocol,research
Classifier: Development Status :: 4 - Beta
Classifier: Intended Audience :: Developers
Classifier: Intended Audience :: Science/Research
Classifier: License :: OSI Approved :: MIT License
Classifier: Operating System :: OS Independent
Classifier: Programming Language :: Python :: 3
Classifier: Programming Language :: Python :: 3.12
Classifier: Programming Language :: Python :: 3.13
Classifier: Programming Language :: Python :: 3.14
Classifier: Topic :: Internet :: WWW/HTTP :: Indexing/Search
Classifier: Topic :: Scientific/Engineering :: Artificial Intelligence
Classifier: Typing :: Typed
Requires-Python: >=3.12
Requires-Dist: google-genai>=1.60.0
Requires-Dist: httpx>=0.28.1
Requires-Dist: mcp<2.0.0,>=1.26.0
Requires-Dist: platformdirs>=4.5.1
Requires-Dist: py-key-value-aio[disk]>=0.3.0
Requires-Dist: python-dotenv>=1.2.1
Provides-Extra: dev
Requires-Dist: marko>=2.2.2; extra == 'dev'
Requires-Dist: mypy>=1.10.0; extra == 'dev'
Requires-Dist: pygments>=2.19.2; extra == 'dev'
Requires-Dist: pytest-asyncio>=0.23.0; extra == 'dev'
Requires-Dist: pytest-cov>=4.0.0; extra == 'dev'
Requires-Dist: pytest-timeout>=2.3.0; extra == 'dev'
Requires-Dist: pytest>=8.0.0; extra == 'dev'
Requires-Dist: python-docx>=1.2.0; extra == 'dev'
Requires-Dist: ruff>=0.4.0; extra == 'dev'
Requires-Dist: types-pygments>=2.19.0; extra == 'dev'
Provides-Extra: docx
Requires-Dist: marko>=2.2.2; extra == 'docx'
Requires-Dist: pygments>=2.19.2; extra == 'docx'
Requires-Dist: python-docx>=1.2.0; extra == 'docx'
